odoo/addons/l10n_ro_partner_create_by_vat/README.rst
odoo/addons/l10n_ro_partner_create_by_vat/__init__.py
odoo/addons/l10n_ro_partner_create_by_vat/__manifest__.py
odoo/addons/l10n_ro_partner_create_by_vat/i18n/l10n_ro_partner_create_by_vat.pot
odoo/addons/l10n_ro_partner_create_by_vat/i18n/ro.po
odoo/addons/l10n_ro_partner_create_by_vat/models/__init__.py
odoo/addons/l10n_ro_partner_create_by_vat/models/res_partner.py
odoo/addons/l10n_ro_partner_create_by_vat/models/res_partner_anaf_scptva.py
odoo/addons/l10n_ro_partner_create_by_vat/models/res_partner_anaf_status.py
odoo/addons/l10n_ro_partner_create_by_vat/readme/CONTRIBUTORS.md
odoo/addons/l10n_ro_partner_create_by_vat/readme/DESCRIPTION.md
odoo/addons/l10n_ro_partner_create_by_vat/readme/INSTALL.md
odoo/addons/l10n_ro_partner_create_by_vat/readme/USAGE.md
odoo/addons/l10n_ro_partner_create_by_vat/security/ir.model.access.csv
odoo/addons/l10n_ro_partner_create_by_vat/static/description/icon.png
odoo/addons/l10n_ro_partner_create_by_vat/static/description/index.html
odoo/addons/l10n_ro_partner_create_by_vat/tests/__init__.py
odoo/addons/l10n_ro_partner_create_by_vat/tests/anaf_data.py
odoo/addons/l10n_ro_partner_create_by_vat/tests/test_create_partner_by_vat.py
odoo/addons/l10n_ro_partner_create_by_vat/views/partner_view.xml
odoo_addon_l10n_ro_partner_create_by_vat-19.0.0.4.0.1.dist-info/METADATA
odoo_addon_l10n_ro_partner_create_by_vat-19.0.0.4.0.1.dist-info/WHEEL
odoo_addon_l10n_ro_partner_create_by_vat-19.0.0.4.0.1.dist-info/top_level.txt
odoo_addon_l10n_ro_partner_create_by_vat-19.0.0.4.0.1.dist-info/RECORD
